poet/__init__.py
poet/__main__.py
poet/lint.py
poet/poet.py
poet/templates.py
poet/util.py
poet/version.py
homebrew_python_poet-0.0.1.dist-info/LICENSE
homebrew_python_poet-0.0.1.dist-info/METADATA
homebrew_python_poet-0.0.1.dist-info/WHEEL
homebrew_python_poet-0.0.1.dist-info/entry_points.txt
homebrew_python_poet-0.0.1.dist-info/top_level.txt
homebrew_python_poet-0.0.1.dist-info/RECORD
